rocksdb/__init__.py
rocksdb/_rocksdb.cpython-310-x86_64-linux-gnu.so
rocksdb/_rocksdb.pyx
rocksdb/errors.py
rocksdb/interfaces.py
rocksdb/merge_operators.py
rocksdb/tests/__init__.py
rocksdb/tests/test_db.py
rocksdb/tests/test_memtable.py
rocksdb/tests/test_options.py
py3_rocksdb-0.7.0.dist-info/LICENCE
py3_rocksdb-0.7.0.dist-info/METADATA
py3_rocksdb-0.7.0.dist-info/WHEEL
py3_rocksdb-0.7.0.dist-info/top_level.txt
py3_rocksdb-0.7.0.dist-info/RECORD
